{
  "resolvedId": "/Users/afeng/Desktop/work/gdpayh5-web/src/pages/Auth/Country.vue?vue&type=script&setup=true&lang.ts",
  "transforms": [
    {
      "name": "vite:vue",
      "result": "import { defineComponent as _defineComponent } from 'vue'\nimport { createCommentVNode as _createCommentVNode, createElementVNode as _createElementVNode, resolveComponent as _resolveComponent, withCtx as _withCtx, createVNode as _createVNode, renderList as _renderList, Fragment as _Fragment, openBlock as _openBlock, createElementBlock as _createElementBlock, unref as _unref, toDisplayString as _toDisplayString, pushScopeId as _pushScopeId, popScopeId as _popScopeId } from \"vue\"\n\nconst _withScopeId = n => (_pushScopeId(\"data-v-d3f1b2ba\"),n=n(),_popScopeId(),n)\nconst _hoisted_1 = { class: \"country bg-[#fff] h-[100vh] z-[20000]\" }\nconst _hoisted_2 = /*#__PURE__*/ _withScopeId(() => /*#__PURE__*/_createElementVNode(\"div\", { class: \"px-[20px]\" }, [\n  /*#__PURE__*/_createElementVNode(\"p\", { class: \"h-[70px] text-[29px] mb-[10px] flex_s text-[#666666] border_p\" }, \"国家/地区\")\n], -1 /* HOISTED */))\nconst _hoisted_3 = [\"onClick\"]\nconst _hoisted_4 = [\"src\"]\nconst _hoisted_5 = { class: \"absolute right-[20px]\" }\n\nimport { requireImg } from '@/utils/tools'\nimport { storeToRefs } from 'pinia'\nimport { ToastOptions, showToast } from 'vant'\nimport { computed, reactive, ref, watch } from 'vue'\nimport { useRoute, useRouter } from 'vue-router'\nimport { ResCountryCode, ResCountryCodeObj, wallet_type } from '@/apis/auth'\n\nimport { defineComponent } from 'vue'\nconst fromPath = ref('/auth/login')\nconst __default__ = defineComponent({\n  beforeRouteEnter(to, from, next) {\n    // next() 可以通过内部的回调函数访问实例\n    fromPath.value = from.path\n    // console.log('fromPath.value', fromPath.value)\n    next(e => {\n      // window.console.log(e) // 当前的this\n    })\n  }\n})\n\nexport default /*#__PURE__*/_defineComponent({\n  ...__default__,\n  __name: 'Country',\n  setup(__props) {\n\nconst router = useRouter()\nconst route = useRouter()\n// console.log('route', route)\n\nconst value = ref('')\nconst list = ref([] as ResCountryCodeObj[])\nconst list2 = ref([] as ResCountryCodeObj[])\nlet t: any = null\nconst onSearch = (val: string) => {\n  clearTimeout(t)\n  t = setTimeout(() => {\n    if (!!!val) {\n      list.value = list2.value\n    } else {\n      list.value = list2.value.filter(e => {\n        // console.log('e', e.country_name)\n        return (\n          e.country_name.includes(val.toUpperCase()) ||\n          e.country_name.includes(val.toLowerCase()) ||\n          e.country_name.toLowerCase().includes(val.toLowerCase()) ||\n          e.country_name.toUpperCase().includes(val.toUpperCase()) ||\n          e.country_name.includes(val) ||\n          e.phone_code.includes(val.toLowerCase())\n        )\n      })\n    }\n  }, 500)\n}\nconst oncancel = () => {\n  // showToast('取消')\n  router.replace(fromPath.value)\n}\nconst gopath = (item: { country_code: string; phone_code: string | number }) => {\n  let path =\n    fromPath.value + '?country_code=' + item.country_code + '&phone_code=' + +item.phone_code\n  // console.log(path)\n  router.replace(path)\n}\n\nwallet_type({}).then(data => {\n  // console.log('data', data)\n  if (!!!data.country_coin.length) return showToast('数据异常')\n  list.value = data.country_coin\n  list2.value = data.country_coin\n})\n\nreturn (_ctx: any,_cache: any) => {\n  const _component_van_search = _resolveComponent(\"van-search\")!\n\n  return (_openBlock(), _createElementBlock(\"div\", _hoisted_1, [\n    _createCommentVNode(\" <form action=\\\"/\\\"> \"),\n    _createVNode(_component_van_search, {\n      modelValue: value.value,\n      \"onUpdate:modelValue\": [\n        _cache[0] || (_cache[0] = ($event: any) => ((value).value = $event)),\n        onSearch\n      ],\n      \"show-action\": \"\",\n      placeholder: \"请输入搜索关键词\",\n      onSearch: onSearch\n    }, {\n      action: _withCtx(() => [\n        _createElementVNode(\"div\", { onClick: oncancel }, \"取消\")\n      ]),\n      _: 1 /* STABLE */\n    }, 8 /* PROPS */, [\"modelValue\"]),\n    _createCommentVNode(\" </form> \"),\n    _hoisted_2,\n    _createElementVNode(\"ul\", null, [\n      (_openBlock(true), _createElementBlock(_Fragment, null, _renderList(list.value, (item) => {\n        return (_openBlock(), _createElementBlock(\"li\", {\n          class: \"flex_s w-[100%] h-[80px] text-[29px] px-[20px]\",\n          key: item.id,\n          onClick: ($event: any) => (gopath(item))\n        }, [\n          _createElementVNode(\"img\", {\n            class: \"h-[65%] mr-[13px]\",\n            src: _unref(requireImg)('common/' + item.country_code + '.png'),\n            alt: \"\"\n          }, null, 8 /* PROPS */, _hoisted_4),\n          _createElementVNode(\"span\", null, _toDisplayString(item.country_name), 1 /* TEXT */),\n          _createElementVNode(\"span\", _hoisted_5, _toDisplayString(item.phone_code), 1 /* TEXT */)\n        ], 8 /* PROPS */, _hoisted_3))\n      }), 128 /* KEYED_FRAGMENT */))\n    ])\n  ]))\n}\n}\n\n})",
      "start": 1714699770476,
      "end": 1714699770476
    },
    {
      "name": "vite:css",
      "start": 1714699770476,
      "end": 1714699770476,
      "order": "normal"
    },
    {
      "name": "vite:esbuild",
      "result": "import { defineComponent as _defineComponent } from \"vue\";\nimport { createCommentVNode as _createCommentVNode, createElementVNode as _createElementVNode, resolveComponent as _resolveComponent, withCtx as _withCtx, createVNode as _createVNode, renderList as _renderList, Fragment as _Fragment, openBlock as _openBlock, createElementBlock as _createElementBlock, unref as _unref, toDisplayString as _toDisplayString, pushScopeId as _pushScopeId, popScopeId as _popScopeId } from \"vue\";\nconst _withScopeId = (n) => (_pushScopeId(\"data-v-d3f1b2ba\"), n = n(), _popScopeId(), n);\nconst _hoisted_1 = { class: \"country bg-[#fff] h-[100vh] z-[20000]\" };\nconst _hoisted_2 = /* @__PURE__ */ _withScopeId(() => /* @__PURE__ */ _createElementVNode(\n  \"div\",\n  { class: \"px-[20px]\" },\n  [\n    /* @__PURE__ */ _createElementVNode(\"p\", { class: \"h-[70px] text-[29px] mb-[10px] flex_s text-[#666666] border_p\" }, \"国家/地区\")\n  ],\n  -1\n  /* HOISTED */\n));\nconst _hoisted_3 = [\"onClick\"];\nconst _hoisted_4 = [\"src\"];\nconst _hoisted_5 = { class: \"absolute right-[20px]\" };\nimport { requireImg } from \"@/utils/tools\";\nimport { showToast } from \"vant\";\nimport { ref } from \"vue\";\nimport { useRouter } from \"vue-router\";\nimport { wallet_type } from \"@/apis/auth\";\nimport { defineComponent } from \"vue\";\nconst fromPath = ref(\"/auth/login\");\nconst __default__ = defineComponent({\n  beforeRouteEnter(to, from, next) {\n    fromPath.value = from.path;\n    next((e) => {\n    });\n  }\n});\nexport default /* @__PURE__ */ _defineComponent({\n  ...__default__,\n  __name: \"Country\",\n  setup(__props) {\n    const router = useRouter();\n    const route = useRouter();\n    const value = ref(\"\");\n    const list = ref([]);\n    const list2 = ref([]);\n    let t = null;\n    const onSearch = (val) => {\n      clearTimeout(t);\n      t = setTimeout(() => {\n        if (!!!val) {\n          list.value = list2.value;\n        } else {\n          list.value = list2.value.filter((e) => {\n            return e.country_name.includes(val.toUpperCase()) || e.country_name.includes(val.toLowerCase()) || e.country_name.toLowerCase().includes(val.toLowerCase()) || e.country_name.toUpperCase().includes(val.toUpperCase()) || e.country_name.includes(val) || e.phone_code.includes(val.toLowerCase());\n          });\n        }\n      }, 500);\n    };\n    const oncancel = () => {\n      router.replace(fromPath.value);\n    };\n    const gopath = (item) => {\n      let path = fromPath.value + \"?country_code=\" + item.country_code + \"&phone_code=\" + +item.phone_code;\n      router.replace(path);\n    };\n    wallet_type({}).then((data) => {\n      if (!!!data.country_coin.length)\n        return showToast(\"数据异常\");\n      list.value = data.country_coin;\n      list2.value = data.country_coin;\n    });\n    return (_ctx, _cache) => {\n      const _component_van_search = _resolveComponent(\"van-search\");\n      return _openBlock(), _createElementBlock(\"div\", _hoisted_1, [\n        _createCommentVNode(' <form action=\"/\"> '),\n        _createVNode(_component_van_search, {\n          modelValue: value.value,\n          \"onUpdate:modelValue\": [\n            _cache[0] || (_cache[0] = ($event) => value.value = $event),\n            onSearch\n          ],\n          \"show-action\": \"\",\n          placeholder: \"请输入搜索关键词\",\n          onSearch\n        }, {\n          action: _withCtx(() => [\n            _createElementVNode(\"div\", { onClick: oncancel }, \"取消\")\n          ]),\n          _: 1\n          /* STABLE */\n        }, 8, [\"modelValue\"]),\n        _createCommentVNode(\" </form> \"),\n        _hoisted_2,\n        _createElementVNode(\"ul\", null, [\n          (_openBlock(true), _createElementBlock(\n            _Fragment,\n            null,\n            _renderList(list.value, (item) => {\n              return _openBlock(), _createElementBlock(\"li\", {\n                class: \"flex_s w-[100%] h-[80px] text-[29px] px-[20px]\",\n                key: item.id,\n                onClick: ($event) => gopath(item)\n              }, [\n                _createElementVNode(\"img\", {\n                  class: \"h-[65%] mr-[13px]\",\n                  src: _unref(requireImg)(\"common/\" + item.country_code + \".png\"),\n                  alt: \"\"\n                }, null, 8, _hoisted_4),\n                _createElementVNode(\n                  \"span\",\n                  null,\n                  _toDisplayString(item.country_name),\n                  1\n                  /* TEXT */\n                ),\n                _createElementVNode(\n                  \"span\",\n                  _hoisted_5,\n                  _toDisplayString(item.phone_code),\n                  1\n                  /* TEXT */\n                )\n              ], 8, _hoisted_3);\n            }),\n            128\n            /* KEYED_FRAGMENT */\n          ))\n        ])\n      ]);\n    };\n  }\n});\n",
      "start": 1714699770477,
      "end": 1714699770708,
      "order": "normal",
      "sourcemaps": {
        "version": 3,
        "sources": [
          "/Users/afeng/Desktop/work/gdpayh5-web/src/pages/Auth/Country.vue?vue&type=script&setup=true&lang.ts"
        ],
        "sourcesContent": [
          "import { defineComponent as _defineComponent } from 'vue'\nimport { createCommentVNode as _createCommentVNode, createElementVNode as _createElementVNode, resolveComponent as _resolveComponent, withCtx as _withCtx, createVNode as _createVNode, renderList as _renderList, Fragment as _Fragment, openBlock as _openBlock, createElementBlock as _createElementBlock, unref as _unref, toDisplayString as _toDisplayString, pushScopeId as _pushScopeId, popScopeId as _popScopeId } from \"vue\"\n\nconst _withScopeId = n => (_pushScopeId(\"data-v-d3f1b2ba\"),n=n(),_popScopeId(),n)\nconst _hoisted_1 = { class: \"country bg-[#fff] h-[100vh] z-[20000]\" }\nconst _hoisted_2 = /*#__PURE__*/ _withScopeId(() => /*#__PURE__*/_createElementVNode(\"div\", { class: \"px-[20px]\" }, [\n  /*#__PURE__*/_createElementVNode(\"p\", { class: \"h-[70px] text-[29px] mb-[10px] flex_s text-[#666666] border_p\" }, \"国家/地区\")\n], -1 /* HOISTED */))\nconst _hoisted_3 = [\"onClick\"]\nconst _hoisted_4 = [\"src\"]\nconst _hoisted_5 = { class: \"absolute right-[20px]\" }\n\nimport { requireImg } from '@/utils/tools'\nimport { storeToRefs } from 'pinia'\nimport { ToastOptions, showToast } from 'vant'\nimport { computed, reactive, ref, watch } from 'vue'\nimport { useRoute, useRouter } from 'vue-router'\nimport { ResCountryCode, ResCountryCodeObj, wallet_type } from '@/apis/auth'\n\nimport { defineComponent } from 'vue'\nconst fromPath = ref('/auth/login')\nconst __default__ = defineComponent({\n  beforeRouteEnter(to, from, next) {\n    // next() 可以通过内部的回调函数访问实例\n    fromPath.value = from.path\n    // console.log('fromPath.value', fromPath.value)\n    next(e => {\n      // window.console.log(e) // 当前的this\n    })\n  }\n})\n\nexport default /*#__PURE__*/_defineComponent({\n  ...__default__,\n  __name: 'Country',\n  setup(__props) {\n\nconst router = useRouter()\nconst route = useRouter()\n// console.log('route', route)\n\nconst value = ref('')\nconst list = ref([] as ResCountryCodeObj[])\nconst list2 = ref([] as ResCountryCodeObj[])\nlet t: any = null\nconst onSearch = (val: string) => {\n  clearTimeout(t)\n  t = setTimeout(() => {\n    if (!!!val) {\n      list.value = list2.value\n    } else {\n      list.value = list2.value.filter(e => {\n        // console.log('e', e.country_name)\n        return (\n          e.country_name.includes(val.toUpperCase()) ||\n          e.country_name.includes(val.toLowerCase()) ||\n          e.country_name.toLowerCase().includes(val.toLowerCase()) ||\n          e.country_name.toUpperCase().includes(val.toUpperCase()) ||\n          e.country_name.includes(val) ||\n          e.phone_code.includes(val.toLowerCase())\n        )\n      })\n    }\n  }, 500)\n}\nconst oncancel = () => {\n  // showToast('取消')\n  router.replace(fromPath.value)\n}\nconst gopath = (item: { country_code: string; phone_code: string | number }) => {\n  let path =\n    fromPath.value + '?country_code=' + item.country_code + '&phone_code=' + +item.phone_code\n  // console.log(path)\n  router.replace(path)\n}\n\nwallet_type({}).then(data => {\n  // console.log('data', data)\n  if (!!!data.country_coin.length) return showToast('数据异常')\n  list.value = data.country_coin\n  list2.value = data.country_coin\n})\n\nreturn (_ctx: any,_cache: any) => {\n  const _component_van_search = _resolveComponent(\"van-search\")!\n\n  return (_openBlock(), _createElementBlock(\"div\", _hoisted_1, [\n    _createCommentVNode(\" <form action=\\\"/\\\"> \"),\n    _createVNode(_component_van_search, {\n      modelValue: value.value,\n      \"onUpdate:modelValue\": [\n        _cache[0] || (_cache[0] = ($event: any) => ((value).value = $event)),\n        onSearch\n      ],\n      \"show-action\": \"\",\n      placeholder: \"请输入搜索关键词\",\n      onSearch: onSearch\n    }, {\n      action: _withCtx(() => [\n        _createElementVNode(\"div\", { onClick: oncancel }, \"取消\")\n      ]),\n      _: 1 /* STABLE */\n    }, 8 /* PROPS */, [\"modelValue\"]),\n    _createCommentVNode(\" </form> \"),\n    _hoisted_2,\n    _createElementVNode(\"ul\", null, [\n      (_openBlock(true), _createElementBlock(_Fragment, null, _renderList(list.value, (item) => {\n        return (_openBlock(), _createElementBlock(\"li\", {\n          class: \"flex_s w-[100%] h-[80px] text-[29px] px-[20px]\",\n          key: item.id,\n          onClick: ($event: any) => (gopath(item))\n        }, [\n          _createElementVNode(\"img\", {\n            class: \"h-[65%] mr-[13px]\",\n            src: _unref(requireImg)('common/' + item.country_code + '.png'),\n            alt: \"\"\n          }, null, 8 /* PROPS */, _hoisted_4),\n          _createElementVNode(\"span\", null, _toDisplayString(item.country_name), 1 /* TEXT */),\n          _createElementVNode(\"span\", _hoisted_5, _toDisplayString(item.phone_code), 1 /* TEXT */)\n        ], 8 /* PROPS */, _hoisted_3))\n      }), 128 /* KEYED_FRAGMENT */))\n    ])\n  ]))\n}\n}\n\n})"
        ],
        "mappings": "AAAA,SAAS,mBAAmB,wBAAwB;AACpD,SAAS,sBAAsB,qBAAqB,sBAAsB,qBAAqB,oBAAoB,mBAAmB,WAAW,UAAU,eAAe,cAAc,cAAc,aAAa,YAAY,WAAW,aAAa,YAAY,sBAAsB,qBAAqB,SAAS,QAAQ,mBAAmB,kBAAkB,eAAe,cAAc,cAAc,mBAAmB;AAEla,MAAM,eAAe,QAAM,aAAa,iBAAiB,GAAE,IAAE,EAAE,GAAE,YAAY,GAAE;AAC/E,MAAM,aAAa,EAAE,OAAO,wCAAwC;AACpE,MAAM,aAA2B,6BAAa,MAAmB;AAAA,EAAoB;AAAA,EAAO,EAAE,OAAO,YAAY;AAAA,EAAG;AAAA,IACrG,oCAAoB,KAAK,EAAE,OAAO,gEAAgE,GAAG,OAAO;AAAA,EAC3H;AAAA,EAAG;AAAA;AAAgB,CAAC;AACpB,MAAM,aAAa,CAAC,SAAS;AAC7B,MAAM,aAAa,CAAC,KAAK;AACzB,MAAM,aAAa,EAAE,OAAO,wBAAwB;AAEpD,SAAS,kBAAkB;AAE3B,SAAuB,iBAAiB;AACxC,SAA6B,WAAkB;AAC/C,SAAmB,iBAAiB;AACpC,SAA4C,mBAAmB;AAE/D,SAAS,uBAAuB;AAChC,MAAM,WAAW,IAAI,aAAa;AAClC,MAAM,cAAc,gBAAgB;AAAA,EAClC,iBAAiB,IAAI,MAAM,MAAM;AAE/B,aAAS,QAAQ,KAAK;AAEtB,SAAK,OAAK;AAAA,IAEV,CAAC;AAAA,EACH;AACF,CAAC;AAED,eAA4B,iCAAiB;AAAA,EAC3C,GAAG;AAAA,EACH,QAAQ;AAAA,EACR,MAAM,SAAS;AAEjB,UAAM,SAAS,UAAU;AACzB,UAAM,QAAQ,UAAU;AAGxB,UAAM,QAAQ,IAAI,EAAE;AACpB,UAAM,OAAO,IAAI,CAAC,CAAwB;AAC1C,UAAM,QAAQ,IAAI,CAAC,CAAwB;AAC3C,QAAI,IAAS;AACb,UAAM,WAAW,CAAC,QAAgB;AAChC,mBAAa,CAAC;AACd,UAAI,WAAW,MAAM;AACnB,YAAI,CAAC,CAAC,CAAC,KAAK;AACV,eAAK,QAAQ,MAAM;AAAA,QACrB,OAAO;AACL,eAAK,QAAQ,MAAM,MAAM,OAAO,OAAK;AAEnC,mBACE,EAAE,aAAa,SAAS,IAAI,YAAY,CAAC,KACzC,EAAE,aAAa,SAAS,IAAI,YAAY,CAAC,KACzC,EAAE,aAAa,YAAY,EAAE,SAAS,IAAI,YAAY,CAAC,KACvD,EAAE,aAAa,YAAY,EAAE,SAAS,IAAI,YAAY,CAAC,KACvD,EAAE,aAAa,SAAS,GAAG,KAC3B,EAAE,WAAW,SAAS,IAAI,YAAY,CAAC;AAAA,UAE3C,CAAC;AAAA,QACH;AAAA,MACF,GAAG,GAAG;AAAA,IACR;AACA,UAAM,WAAW,MAAM;AAErB,aAAO,QAAQ,SAAS,KAAK;AAAA,IAC/B;AACA,UAAM,SAAS,CAAC,SAAgE;AAC9E,UAAI,OACF,SAAS,QAAQ,mBAAmB,KAAK,eAAe,iBAAiB,CAAC,KAAK;AAEjF,aAAO,QAAQ,IAAI;AAAA,IACrB;AAEA,gBAAY,CAAC,CAAC,EAAE,KAAK,UAAQ;AAE3B,UAAI,CAAC,CAAC,CAAC,KAAK,aAAa;AAAQ,eAAO,UAAU,MAAM;AACxD,WAAK,QAAQ,KAAK;AAClB,YAAM,QAAQ,KAAK;AAAA,IACrB,CAAC;AAED,WAAO,CAAC,MAAU,WAAgB;AAChC,YAAM,wBAAwB,kBAAkB,YAAY;AAE5D,aAAQ,WAAW,GAAG,oBAAoB,OAAO,YAAY;AAAA,QAC3D,oBAAoB,qBAAuB;AAAA,QAC3C,aAAa,uBAAuB;AAAA,UAClC,YAAY,MAAM;AAAA,UAClB,uBAAuB;AAAA,YACrB,OAAO,CAAC,MAAM,OAAO,CAAC,IAAI,CAAC,WAAkB,MAAO,QAAQ;AAAA,YAC5D;AAAA,UACF;AAAA,UACA,eAAe;AAAA,UACf,aAAa;AAAA,UACb;AAAA,QACF,GAAG;AAAA,UACD,QAAQ,SAAS,MAAM;AAAA,YACrB,oBAAoB,OAAO,EAAE,SAAS,SAAS,GAAG,IAAI;AAAA,UACxD,CAAC;AAAA,UACD,GAAG;AAAA;AAAA,QACL,GAAG,GAAe,CAAC,YAAY,CAAC;AAAA,QAChC,oBAAoB,WAAW;AAAA,QAC/B;AAAA,QACA,oBAAoB,MAAM,MAAM;AAAA,WAC7B,WAAW,IAAI,GAAG;AAAA,YAAoB;AAAA,YAAW;AAAA,YAAM,YAAY,KAAK,OAAO,CAAC,SAAS;AACxF,qBAAQ,WAAW,GAAG,oBAAoB,MAAM;AAAA,gBAC9C,OAAO;AAAA,gBACP,KAAK,KAAK;AAAA,gBACV,SAAS,CAAC,WAAiB,OAAO,IAAI;AAAA,cACxC,GAAG;AAAA,gBACD,oBAAoB,OAAO;AAAA,kBACzB,OAAO;AAAA,kBACP,KAAK,OAAO,UAAU,EAAE,YAAY,KAAK,eAAe,MAAM;AAAA,kBAC9D,KAAK;AAAA,gBACP,GAAG,MAAM,GAAe,UAAU;AAAA,gBAClC;AAAA,kBAAoB;AAAA,kBAAQ;AAAA,kBAAM,iBAAiB,KAAK,YAAY;AAAA,kBAAG;AAAA;AAAA,gBAAY;AAAA,gBACnF;AAAA,kBAAoB;AAAA,kBAAQ;AAAA,kBAAY,iBAAiB,KAAK,UAAU;AAAA,kBAAG;AAAA;AAAA,gBAAY;AAAA,cACzF,GAAG,GAAe,UAAU;AAAA,YAC9B,CAAC;AAAA,YAAG;AAAA;AAAA,UAAwB;AAAA,QAC9B,CAAC;AAAA,MACH,CAAC;AAAA,IACH;AAAA,EACA;AAEA,CAAC;",
        "names": []
      }
    },
    {
      "name": "vite:json",
      "start": 1714699770708,
      "end": 1714699770708,
      "order": "normal"
    },
    {
      "name": "vite:worker",
      "start": 1714699770708,
      "end": 1714699770708,
      "order": "normal"
    },
    {
      "name": "vite:vue",
      "start": 1714699770708,
      "end": 1714699770708,
      "order": "normal"
    },
    {
      "name": "vite:vue-jsx",
      "start": 1714699770708,
      "end": 1714699770708,
      "order": "normal"
    },
    {
      "name": "vite-plugin-vconsole",
      "result": "import { defineComponent as _defineComponent } from \"vue\";\nimport { createCommentVNode as _createCommentVNode, createElementVNode as _createElementVNode, resolveComponent as _resolveComponent, withCtx as _withCtx, createVNode as _createVNode, renderList as _renderList, Fragment as _Fragment, openBlock as _openBlock, createElementBlock as _createElementBlock, unref as _unref, toDisplayString as _toDisplayString, pushScopeId as _pushScopeId, popScopeId as _popScopeId } from \"vue\";\nconst _withScopeId = (n) => (_pushScopeId(\"data-v-d3f1b2ba\"), n = n(), _popScopeId(), n);\nconst _hoisted_1 = { class: \"country bg-[#fff] h-[100vh] z-[20000]\" };\nconst _hoisted_2 = /* @__PURE__ */ _withScopeId(() => /* @__PURE__ */ _createElementVNode(\n  \"div\",\n  { class: \"px-[20px]\" },\n  [\n    /* @__PURE__ */ _createElementVNode(\"p\", { class: \"h-[70px] text-[29px] mb-[10px] flex_s text-[#666666] border_p\" }, \"国家/地区\")\n  ],\n  -1\n  /* HOISTED */\n));\nconst _hoisted_3 = [\"onClick\"];\nconst _hoisted_4 = [\"src\"];\nconst _hoisted_5 = { class: \"absolute right-[20px]\" };\nimport { requireImg } from \"@/utils/tools\";\nimport { showToast } from \"vant\";\nimport { ref } from \"vue\";\nimport { useRouter } from \"vue-router\";\nimport { wallet_type } from \"@/apis/auth\";\nimport { defineComponent } from \"vue\";\nconst fromPath = ref(\"/auth/login\");\nconst __default__ = defineComponent({\n  beforeRouteEnter(to, from, next) {\n    fromPath.value = from.path;\n    next((e) => {\n    });\n  }\n});\nexport default /* @__PURE__ */ _defineComponent({\n  ...__default__,\n  __name: \"Country\",\n  setup(__props) {\n    const router = useRouter();\n    const route = useRouter();\n    const value = ref(\"\");\n    const list = ref([]);\n    const list2 = ref([]);\n    let t = null;\n    const onSearch = (val) => {\n      clearTimeout(t);\n      t = setTimeout(() => {\n        if (!!!val) {\n          list.value = list2.value;\n        } else {\n          list.value = list2.value.filter((e) => {\n            return e.country_name.includes(val.toUpperCase()) || e.country_name.includes(val.toLowerCase()) || e.country_name.toLowerCase().includes(val.toLowerCase()) || e.country_name.toUpperCase().includes(val.toUpperCase()) || e.country_name.includes(val) || e.phone_code.includes(val.toLowerCase());\n          });\n        }\n      }, 500);\n    };\n    const oncancel = () => {\n      router.replace(fromPath.value);\n    };\n    const gopath = (item) => {\n      let path = fromPath.value + \"?country_code=\" + item.country_code + \"&phone_code=\" + +item.phone_code;\n      router.replace(path);\n    };\n    wallet_type({}).then((data) => {\n      if (!!!data.country_coin.length)\n        return showToast(\"数据异常\");\n      list.value = data.country_coin;\n      list2.value = data.country_coin;\n    });\n    return (_ctx, _cache) => {\n      const _component_van_search = _resolveComponent(\"van-search\");\n      return _openBlock(), _createElementBlock(\"div\", _hoisted_1, [\n        _createCommentVNode(' <form action=\"/\"> '),\n        _createVNode(_component_van_search, {\n          modelValue: value.value,\n          \"onUpdate:modelValue\": [\n            _cache[0] || (_cache[0] = ($event) => value.value = $event),\n            onSearch\n          ],\n          \"show-action\": \"\",\n          placeholder: \"请输入搜索关键词\",\n          onSearch\n        }, {\n          action: _withCtx(() => [\n            _createElementVNode(\"div\", { onClick: oncancel }, \"取消\")\n          ]),\n          _: 1\n          /* STABLE */\n        }, 8, [\"modelValue\"]),\n        _createCommentVNode(\" </form> \"),\n        _hoisted_2,\n        _createElementVNode(\"ul\", null, [\n          (_openBlock(true), _createElementBlock(\n            _Fragment,\n            null,\n            _renderList(list.value, (item) => {\n              return _openBlock(), _createElementBlock(\"li\", {\n                class: \"flex_s w-[100%] h-[80px] text-[29px] px-[20px]\",\n                key: item.id,\n                onClick: ($event) => gopath(item)\n              }, [\n                _createElementVNode(\"img\", {\n                  class: \"h-[65%] mr-[13px]\",\n                  src: _unref(requireImg)(\"common/\" + item.country_code + \".png\"),\n                  alt: \"\"\n                }, null, 8, _hoisted_4),\n                _createElementVNode(\n                  \"span\",\n                  null,\n                  _toDisplayString(item.country_name),\n                  1\n                  /* TEXT */\n                ),\n                _createElementVNode(\n                  \"span\",\n                  _hoisted_5,\n                  _toDisplayString(item.phone_code),\n                  1\n                  /* TEXT */\n                )\n              ], 8, _hoisted_3);\n            }),\n            128\n            /* KEYED_FRAGMENT */\n          ))\n        ])\n      ]);\n    };\n  }\n});\n",
      "start": 1714699770708,
      "end": 1714699770708,
      "order": "normal",
      "sourcemaps": null
    },
    {
      "name": "esbuild",
      "result": "\"use strict\";\nimport { defineComponent as _defineComponent } from \"vue\";\nimport { createCommentVNode as _createCommentVNode, createElementVNode as _createElementVNode, resolveComponent as _resolveComponent, withCtx as _withCtx, createVNode as _createVNode, renderList as _renderList, Fragment as _Fragment, openBlock as _openBlock, createElementBlock as _createElementBlock, unref as _unref, toDisplayString as _toDisplayString, pushScopeId as _pushScopeId, popScopeId as _popScopeId } from \"vue\";\nconst _withScopeId = (n) => (_pushScopeId(\"data-v-d3f1b2ba\"), n = n(), _popScopeId(), n);\nconst _hoisted_1 = { class: \"country bg-[#fff] h-[100vh] z-[20000]\" };\nconst _hoisted_2 = /* @__PURE__ */ _withScopeId(() => /* @__PURE__ */ _createElementVNode(\n  \"div\",\n  { class: \"px-[20px]\" },\n  [\n    /* @__PURE__ */ _createElementVNode(\"p\", { class: \"h-[70px] text-[29px] mb-[10px] flex_s text-[#666666] border_p\" }, \"\\u56FD\\u5BB6/\\u5730\\u533A\")\n  ],\n  -1\n  /* HOISTED */\n));\nconst _hoisted_3 = [\"onClick\"];\nconst _hoisted_4 = [\"src\"];\nconst _hoisted_5 = { class: \"absolute right-[20px]\" };\nimport { requireImg } from \"@/utils/tools\";\nimport { showToast } from \"vant\";\nimport { ref } from \"vue\";\nimport { useRouter } from \"vue-router\";\nimport { wallet_type } from \"@/apis/auth\";\nimport { defineComponent } from \"vue\";\nconst fromPath = ref(\"/auth/login\");\nconst __default__ = defineComponent({\n  beforeRouteEnter(to, from, next) {\n    fromPath.value = from.path;\n    next((e) => {\n    });\n  }\n});\nexport default /* @__PURE__ */ _defineComponent({\n  ...__default__,\n  __name: \"Country\",\n  setup(__props) {\n    const router = useRouter();\n    const route = useRouter();\n    const value = ref(\"\");\n    const list = ref([]);\n    const list2 = ref([]);\n    let t = null;\n    const onSearch = (val) => {\n      clearTimeout(t);\n      t = setTimeout(() => {\n        if (!!!val) {\n          list.value = list2.value;\n        } else {\n          list.value = list2.value.filter((e) => {\n            return e.country_name.includes(val.toUpperCase()) || e.country_name.includes(val.toLowerCase()) || e.country_name.toLowerCase().includes(val.toLowerCase()) || e.country_name.toUpperCase().includes(val.toUpperCase()) || e.country_name.includes(val) || e.phone_code.includes(val.toLowerCase());\n          });\n        }\n      }, 500);\n    };\n    const oncancel = () => {\n      router.replace(fromPath.value);\n    };\n    const gopath = (item) => {\n      let path = fromPath.value + \"?country_code=\" + item.country_code + \"&phone_code=\" + +item.phone_code;\n      router.replace(path);\n    };\n    wallet_type({}).then((data) => {\n      if (!!!data.country_coin.length)\n        return showToast(\"\\u6570\\u636E\\u5F02\\u5E38\");\n      list.value = data.country_coin;\n      list2.value = data.country_coin;\n    });\n    return (_ctx, _cache) => {\n      const _component_van_search = _resolveComponent(\"van-search\");\n      return _openBlock(), _createElementBlock(\"div\", _hoisted_1, [\n        _createCommentVNode(' <form action=\"/\"> '),\n        _createVNode(_component_van_search, {\n          modelValue: value.value,\n          \"onUpdate:modelValue\": [\n            _cache[0] || (_cache[0] = ($event) => value.value = $event),\n            onSearch\n          ],\n          \"show-action\": \"\",\n          placeholder: \"\\u8BF7\\u8F93\\u5165\\u641C\\u7D22\\u5173\\u952E\\u8BCD\",\n          onSearch\n        }, {\n          action: _withCtx(() => [\n            _createElementVNode(\"div\", { onClick: oncancel }, \"\\u53D6\\u6D88\")\n          ]),\n          _: 1\n          /* STABLE */\n        }, 8, [\"modelValue\"]),\n        _createCommentVNode(\" </form> \"),\n        _hoisted_2,\n        _createElementVNode(\"ul\", null, [\n          (_openBlock(true), _createElementBlock(\n            _Fragment,\n            null,\n            _renderList(list.value, (item) => {\n              return _openBlock(), _createElementBlock(\"li\", {\n                class: \"flex_s w-[100%] h-[80px] text-[29px] px-[20px]\",\n                key: item.id,\n                onClick: ($event) => gopath(item)\n              }, [\n                _createElementVNode(\"img\", {\n                  class: \"h-[65%] mr-[13px]\",\n                  src: _unref(requireImg)(\"common/\" + item.country_code + \".png\"),\n                  alt: \"\"\n                }, null, 8, _hoisted_4),\n                _createElementVNode(\n                  \"span\",\n                  null,\n                  _toDisplayString(item.country_name),\n                  1\n                  /* TEXT */\n                ),\n                _createElementVNode(\n                  \"span\",\n                  _hoisted_5,\n                  _toDisplayString(item.phone_code),\n                  1\n                  /* TEXT */\n                )\n              ], 8, _hoisted_3);\n            }),\n            128\n            /* KEYED_FRAGMENT */\n          ))\n        ])\n      ]);\n    };\n  }\n});\n",
      "start": 1714699770708,
      "end": 1714699771647,
      "order": "normal",
      "sourcemaps": "{\n  \"version\": 3,\n  \"sources\": [\"/Users/afeng/Desktop/work/gdpayh5-web/src/pages/Auth/Country.vue?vue&type=script&setup=true&lang.ts\"],\n  \"sourcesContent\": [\"import { defineComponent as _defineComponent } from \\\"vue\\\";\\nimport { createCommentVNode as _createCommentVNode, createElementVNode as _createElementVNode, resolveComponent as _resolveComponent, withCtx as _withCtx, createVNode as _createVNode, renderList as _renderList, Fragment as _Fragment, openBlock as _openBlock, createElementBlock as _createElementBlock, unref as _unref, toDisplayString as _toDisplayString, pushScopeId as _pushScopeId, popScopeId as _popScopeId } from \\\"vue\\\";\\nconst _withScopeId = (n) => (_pushScopeId(\\\"data-v-d3f1b2ba\\\"), n = n(), _popScopeId(), n);\\nconst _hoisted_1 = { class: \\\"country bg-[#fff] h-[100vh] z-[20000]\\\" };\\nconst _hoisted_2 = /* @__PURE__ */ _withScopeId(() => /* @__PURE__ */ _createElementVNode(\\n  \\\"div\\\",\\n  { class: \\\"px-[20px]\\\" },\\n  [\\n    /* @__PURE__ */ _createElementVNode(\\\"p\\\", { class: \\\"h-[70px] text-[29px] mb-[10px] flex_s text-[#666666] border_p\\\" }, \\\"\\u56FD\\u5BB6/\\u5730\\u533A\\\")\\n  ],\\n  -1\\n  /* HOISTED */\\n));\\nconst _hoisted_3 = [\\\"onClick\\\"];\\nconst _hoisted_4 = [\\\"src\\\"];\\nconst _hoisted_5 = { class: \\\"absolute right-[20px]\\\" };\\nimport { requireImg } from \\\"@/utils/tools\\\";\\nimport { showToast } from \\\"vant\\\";\\nimport { ref } from \\\"vue\\\";\\nimport { useRouter } from \\\"vue-router\\\";\\nimport { wallet_type } from \\\"@/apis/auth\\\";\\nimport { defineComponent } from \\\"vue\\\";\\nconst fromPath = ref(\\\"/auth/login\\\");\\nconst __default__ = defineComponent({\\n  beforeRouteEnter(to, from, next) {\\n    fromPath.value = from.path;\\n    next((e) => {\\n    });\\n  }\\n});\\nexport default /* @__PURE__ */ _defineComponent({\\n  ...__default__,\\n  __name: \\\"Country\\\",\\n  setup(__props) {\\n    const router = useRouter();\\n    const route = useRouter();\\n    const value = ref(\\\"\\\");\\n    const list = ref([]);\\n    const list2 = ref([]);\\n    let t = null;\\n    const onSearch = (val) => {\\n      clearTimeout(t);\\n      t = setTimeout(() => {\\n        if (!!!val) {\\n          list.value = list2.value;\\n        } else {\\n          list.value = list2.value.filter((e) => {\\n            return e.country_name.includes(val.toUpperCase()) || e.country_name.includes(val.toLowerCase()) || e.country_name.toLowerCase().includes(val.toLowerCase()) || e.country_name.toUpperCase().includes(val.toUpperCase()) || e.country_name.includes(val) || e.phone_code.includes(val.toLowerCase());\\n          });\\n        }\\n      }, 500);\\n    };\\n    const oncancel = () => {\\n      router.replace(fromPath.value);\\n    };\\n    const gopath = (item) => {\\n      let path = fromPath.value + \\\"?country_code=\\\" + item.country_code + \\\"&phone_code=\\\" + +item.phone_code;\\n      router.replace(path);\\n    };\\n    wallet_type({}).then((data) => {\\n      if (!!!data.country_coin.length)\\n        return showToast(\\\"\\u6570\\u636E\\u5F02\\u5E38\\\");\\n      list.value = data.country_coin;\\n      list2.value = data.country_coin;\\n    });\\n    return (_ctx, _cache) => {\\n      const _component_van_search = _resolveComponent(\\\"van-search\\\");\\n      return _openBlock(), _createElementBlock(\\\"div\\\", _hoisted_1, [\\n        _createCommentVNode(' <form action=\\\"/\\\"> '),\\n        _createVNode(_component_van_search, {\\n          modelValue: value.value,\\n          \\\"onUpdate:modelValue\\\": [\\n            _cache[0] || (_cache[0] = ($event) => value.value = $event),\\n            onSearch\\n          ],\\n          \\\"show-action\\\": \\\"\\\",\\n          placeholder: \\\"\\u8BF7\\u8F93\\u5165\\u641C\\u7D22\\u5173\\u952E\\u8BCD\\\",\\n          onSearch\\n        }, {\\n          action: _withCtx(() => [\\n            _createElementVNode(\\\"div\\\", { onClick: oncancel }, \\\"\\u53D6\\u6D88\\\")\\n          ]),\\n          _: 1\\n          /* STABLE */\\n        }, 8, [\\\"modelValue\\\"]),\\n        _createCommentVNode(\\\" </form> \\\"),\\n        _hoisted_2,\\n        _createElementVNode(\\\"ul\\\", null, [\\n          (_openBlock(true), _createElementBlock(\\n            _Fragment,\\n            null,\\n            _renderList(list.value, (item) => {\\n              return _openBlock(), _createElementBlock(\\\"li\\\", {\\n                class: \\\"flex_s w-[100%] h-[80px] text-[29px] px-[20px]\\\",\\n                key: item.id,\\n                onClick: ($event) => gopath(item)\\n              }, [\\n                _createElementVNode(\\\"img\\\", {\\n                  class: \\\"h-[65%] mr-[13px]\\\",\\n                  src: _unref(requireImg)(\\\"common/\\\" + item.country_code + \\\".png\\\"),\\n                  alt: \\\"\\\"\\n                }, null, 8, _hoisted_4),\\n                _createElementVNode(\\n                  \\\"span\\\",\\n                  null,\\n                  _toDisplayString(item.country_name),\\n                  1\\n                  /* TEXT */\\n                ),\\n                _createElementVNode(\\n                  \\\"span\\\",\\n                  _hoisted_5,\\n                  _toDisplayString(item.phone_code),\\n                  1\\n                  /* TEXT */\\n                )\\n              ], 8, _hoisted_3);\\n            }),\\n            128\\n            /* KEYED_FRAGMENT */\\n          ))\\n        ])\\n      ]);\\n    };\\n  }\\n});\\n\"],\n  \"mappings\": \";AAAA,SAAS,mBAAmB,wBAAwB;AACpD,SAAS,sBAAsB,qBAAqB,sBAAsB,qBAAqB,oBAAoB,mBAAmB,WAAW,UAAU,eAAe,cAAc,cAAc,aAAa,YAAY,WAAW,aAAa,YAAY,sBAAsB,qBAAqB,SAAS,QAAQ,mBAAmB,kBAAkB,eAAe,cAAc,cAAc,mBAAmB;AACla,MAAM,eAAe,CAAC,OAAO,aAAa,iBAAiB,GAAG,IAAI,EAAE,GAAG,YAAY,GAAG;AACtF,MAAM,aAAa,EAAE,OAAO,wCAAwC;AACpE,MAAM,aAA6B,6BAAa,MAAsB;AAAA,EACpE;AAAA,EACA,EAAE,OAAO,YAAY;AAAA,EACrB;AAAA,IACkB,oCAAoB,KAAK,EAAE,OAAO,gEAAgE,GAAG,2BAAO;AAAA,EAC9H;AAAA,EACA;AAAA;AAEF,CAAC;AACD,MAAM,aAAa,CAAC,SAAS;AAC7B,MAAM,aAAa,CAAC,KAAK;AACzB,MAAM,aAAa,EAAE,OAAO,wBAAwB;AACpD,SAAS,kBAAkB;AAC3B,SAAS,iBAAiB;AAC1B,SAAS,WAAW;AACpB,SAAS,iBAAiB;AAC1B,SAAS,mBAAmB;AAC5B,SAAS,uBAAuB;AAChC,MAAM,WAAW,IAAI,aAAa;AAClC,MAAM,cAAc,gBAAgB;AAAA,EAClC,iBAAiB,IAAI,MAAM,MAAM;AAC/B,aAAS,QAAQ,KAAK;AACtB,SAAK,CAAC,MAAM;AAAA,IACZ,CAAC;AAAA,EACH;AACF,CAAC;AACD,eAA+B,iCAAiB;AAAA,EAC9C,GAAG;AAAA,EACH,QAAQ;AAAA,EACR,MAAM,SAAS;AACb,UAAM,SAAS,UAAU;AACzB,UAAM,QAAQ,UAAU;AACxB,UAAM,QAAQ,IAAI,EAAE;AACpB,UAAM,OAAO,IAAI,CAAC,CAAC;AACnB,UAAM,QAAQ,IAAI,CAAC,CAAC;AACpB,QAAI,IAAI;AACR,UAAM,WAAW,CAAC,QAAQ;AACxB,mBAAa,CAAC;AACd,UAAI,WAAW,MAAM;AACnB,YAAI,CAAC,CAAC,CAAC,KAAK;AACV,eAAK,QAAQ,MAAM;AAAA,QACrB,OAAO;AACL,eAAK,QAAQ,MAAM,MAAM,OAAO,CAAC,MAAM;AACrC,mBAAO,EAAE,aAAa,SAAS,IAAI,YAAY,CAAC,KAAK,EAAE,aAAa,SAAS,IAAI,YAAY,CAAC,KAAK,EAAE,aAAa,YAAY,EAAE,SAAS,IAAI,YAAY,CAAC,KAAK,EAAE,aAAa,YAAY,EAAE,SAAS,IAAI,YAAY,CAAC,KAAK,EAAE,aAAa,SAAS,GAAG,KAAK,EAAE,WAAW,SAAS,IAAI,YAAY,CAAC;AAAA,UACpS,CAAC;AAAA,QACH;AAAA,MACF,GAAG,GAAG;AAAA,IACR;AACA,UAAM,WAAW,MAAM;AACrB,aAAO,QAAQ,SAAS,KAAK;AAAA,IAC/B;AACA,UAAM,SAAS,CAAC,SAAS;AACvB,UAAI,OAAO,SAAS,QAAQ,mBAAmB,KAAK,eAAe,iBAAiB,CAAC,KAAK;AAC1F,aAAO,QAAQ,IAAI;AAAA,IACrB;AACA,gBAAY,CAAC,CAAC,EAAE,KAAK,CAAC,SAAS;AAC7B,UAAI,CAAC,CAAC,CAAC,KAAK,aAAa;AACvB,eAAO,UAAU,0BAAM;AACzB,WAAK,QAAQ,KAAK;AAClB,YAAM,QAAQ,KAAK;AAAA,IACrB,CAAC;AACD,WAAO,CAAC,MAAM,WAAW;AACvB,YAAM,wBAAwB,kBAAkB,YAAY;AAC5D,aAAO,WAAW,GAAG,oBAAoB,OAAO,YAAY;AAAA,QAC1D,oBAAoB,qBAAqB;AAAA,QACzC,aAAa,uBAAuB;AAAA,UAClC,YAAY,MAAM;AAAA,UAClB,uBAAuB;AAAA,YACrB,OAAO,CAAC,MAAM,OAAO,CAAC,IAAI,CAAC,WAAW,MAAM,QAAQ;AAAA,YACpD;AAAA,UACF;AAAA,UACA,eAAe;AAAA,UACf,aAAa;AAAA,UACb;AAAA,QACF,GAAG;AAAA,UACD,QAAQ,SAAS,MAAM;AAAA,YACrB,oBAAoB,OAAO,EAAE,SAAS,SAAS,GAAG,cAAI;AAAA,UACxD,CAAC;AAAA,UACD,GAAG;AAAA;AAAA,QAEL,GAAG,GAAG,CAAC,YAAY,CAAC;AAAA,QACpB,oBAAoB,WAAW;AAAA,QAC/B;AAAA,QACA,oBAAoB,MAAM,MAAM;AAAA,WAC7B,WAAW,IAAI,GAAG;AAAA,YACjB;AAAA,YACA;AAAA,YACA,YAAY,KAAK,OAAO,CAAC,SAAS;AAChC,qBAAO,WAAW,GAAG,oBAAoB,MAAM;AAAA,gBAC7C,OAAO;AAAA,gBACP,KAAK,KAAK;AAAA,gBACV,SAAS,CAAC,WAAW,OAAO,IAAI;AAAA,cAClC,GAAG;AAAA,gBACD,oBAAoB,OAAO;AAAA,kBACzB,OAAO;AAAA,kBACP,KAAK,OAAO,UAAU,EAAE,YAAY,KAAK,eAAe,MAAM;AAAA,kBAC9D,KAAK;AAAA,gBACP,GAAG,MAAM,GAAG,UAAU;AAAA,gBACtB;AAAA,kBACE;AAAA,kBACA;AAAA,kBACA,iBAAiB,KAAK,YAAY;AAAA,kBAClC;AAAA;AAAA,gBAEF;AAAA,gBACA;AAAA,kBACE;AAAA,kBACA;AAAA,kBACA,iBAAiB,KAAK,UAAU;AAAA,kBAChC;AAAA;AAAA,gBAEF;AAAA,cACF,GAAG,GAAG,UAAU;AAAA,YAClB,CAAC;AAAA,YACD;AAAA;AAAA,UAEF;AAAA,QACF,CAAC;AAAA,MACH,CAAC;AAAA,IACH;AAAA,EACF;AACF,CAAC;\",\n  \"names\": []\n}\n"
    },
    {
      "name": "vite:define",
      "start": 1714699771648,
      "end": 1714699771648,
      "order": "normal"
    },
    {
      "name": "vite:css-post",
      "start": 1714699771648,
      "end": 1714699771648,
      "order": "normal"
    },
    {
      "name": "vite:build-html",
      "start": 1714699771648,
      "end": 1714699771648,
      "order": "normal"
    },
    {
      "name": "vite:worker-import-meta-url",
      "start": 1714699771648,
      "end": 1714699771648,
      "order": "normal"
    },
    {
      "name": "vite:asset-import-meta-url",
      "start": 1714699771648,
      "end": 1714699771648,
      "order": "normal"
    },
    {
      "name": "commonjs",
      "start": 1714699771648,
      "end": 1714699771648,
      "order": "normal"
    },
    {
      "name": "vite:dynamic-import-vars",
      "start": 1714699771648,
      "end": 1714699771648,
      "order": "normal"
    },
    {
      "name": "vite:import-glob",
      "start": 1714699771648,
      "end": 1714699771648,
      "order": "normal"
    },
    {
      "name": "unplugin-auto-import",
      "start": 1714699771648,
      "end": 1714699771649,
      "order": "post"
    },
    {
      "name": "unplugin-vue-components",
      "result": "/* unplugin-vue-components disabled */import { Search as __unplugin_components_0 } from 'vant/es';import 'vant/es/search/style/index';\n\"use strict\";\nimport { defineComponent as _defineComponent } from \"vue\";\nimport { createCommentVNode as _createCommentVNode, createElementVNode as _createElementVNode, resolveComponent as _resolveComponent, withCtx as _withCtx, createVNode as _createVNode, renderList as _renderList, Fragment as _Fragment, openBlock as _openBlock, createElementBlock as _createElementBlock, unref as _unref, toDisplayString as _toDisplayString, pushScopeId as _pushScopeId, popScopeId as _popScopeId } from \"vue\";\nconst _withScopeId = (n) => (_pushScopeId(\"data-v-d3f1b2ba\"), n = n(), _popScopeId(), n);\nconst _hoisted_1 = { class: \"country bg-[#fff] h-[100vh] z-[20000]\" };\nconst _hoisted_2 = /* @__PURE__ */ _withScopeId(() => /* @__PURE__ */ _createElementVNode(\n  \"div\",\n  { class: \"px-[20px]\" },\n  [\n    /* @__PURE__ */ _createElementVNode(\"p\", { class: \"h-[70px] text-[29px] mb-[10px] flex_s text-[#666666] border_p\" }, \"\\u56FD\\u5BB6/\\u5730\\u533A\")\n  ],\n  -1\n  /* HOISTED */\n));\nconst _hoisted_3 = [\"onClick\"];\nconst _hoisted_4 = [\"src\"];\nconst _hoisted_5 = { class: \"absolute right-[20px]\" };\nimport { requireImg } from \"@/utils/tools\";\nimport { showToast } from \"vant\";\nimport { ref } from \"vue\";\nimport { useRouter } from \"vue-router\";\nimport { wallet_type } from \"@/apis/auth\";\nimport { defineComponent } from \"vue\";\nconst fromPath = ref(\"/auth/login\");\nconst __default__ = defineComponent({\n  beforeRouteEnter(to, from, next) {\n    fromPath.value = from.path;\n    next((e) => {\n    });\n  }\n});\nexport default /* @__PURE__ */ _defineComponent({\n  ...__default__,\n  __name: \"Country\",\n  setup(__props) {\n    const router = useRouter();\n    const route = useRouter();\n    const value = ref(\"\");\n    const list = ref([]);\n    const list2 = ref([]);\n    let t = null;\n    const onSearch = (val) => {\n      clearTimeout(t);\n      t = setTimeout(() => {\n        if (!!!val) {\n          list.value = list2.value;\n        } else {\n          list.value = list2.value.filter((e) => {\n            return e.country_name.includes(val.toUpperCase()) || e.country_name.includes(val.toLowerCase()) || e.country_name.toLowerCase().includes(val.toLowerCase()) || e.country_name.toUpperCase().includes(val.toUpperCase()) || e.country_name.includes(val) || e.phone_code.includes(val.toLowerCase());\n          });\n        }\n      }, 500);\n    };\n    const oncancel = () => {\n      router.replace(fromPath.value);\n    };\n    const gopath = (item) => {\n      let path = fromPath.value + \"?country_code=\" + item.country_code + \"&phone_code=\" + +item.phone_code;\n      router.replace(path);\n    };\n    wallet_type({}).then((data) => {\n      if (!!!data.country_coin.length)\n        return showToast(\"\\u6570\\u636E\\u5F02\\u5E38\");\n      list.value = data.country_coin;\n      list2.value = data.country_coin;\n    });\n    return (_ctx, _cache) => {\n      const _component_van_search = __unplugin_components_0;\n      return _openBlock(), _createElementBlock(\"div\", _hoisted_1, [\n        _createCommentVNode(' <form action=\"/\"> '),\n        _createVNode(_component_van_search, {\n          modelValue: value.value,\n          \"onUpdate:modelValue\": [\n            _cache[0] || (_cache[0] = ($event) => value.value = $event),\n            onSearch\n          ],\n          \"show-action\": \"\",\n          placeholder: \"\\u8BF7\\u8F93\\u5165\\u641C\\u7D22\\u5173\\u952E\\u8BCD\",\n          onSearch\n        }, {\n          action: _withCtx(() => [\n            _createElementVNode(\"div\", { onClick: oncancel }, \"\\u53D6\\u6D88\")\n          ]),\n          _: 1\n          /* STABLE */\n        }, 8, [\"modelValue\"]),\n        _createCommentVNode(\" </form> \"),\n        _hoisted_2,\n        _createElementVNode(\"ul\", null, [\n          (_openBlock(true), _createElementBlock(\n            _Fragment,\n            null,\n            _renderList(list.value, (item) => {\n              return _openBlock(), _createElementBlock(\"li\", {\n                class: \"flex_s w-[100%] h-[80px] text-[29px] px-[20px]\",\n                key: item.id,\n                onClick: ($event) => gopath(item)\n              }, [\n                _createElementVNode(\"img\", {\n                  class: \"h-[65%] mr-[13px]\",\n                  src: _unref(requireImg)(\"common/\" + item.country_code + \".png\"),\n                  alt: \"\"\n                }, null, 8, _hoisted_4),\n                _createElementVNode(\n                  \"span\",\n                  null,\n                  _toDisplayString(item.country_name),\n                  1\n                  /* TEXT */\n                ),\n                _createElementVNode(\n                  \"span\",\n                  _hoisted_5,\n                  _toDisplayString(item.phone_code),\n                  1\n                  /* TEXT */\n                )\n              ], 8, _hoisted_3);\n            }),\n            128\n            /* KEYED_FRAGMENT */\n          ))\n        ])\n      ]);\n    };\n  }\n});\n",
      "start": 1714699771649,
      "end": 1714699771649,
      "order": "post",
      "sourcemaps": {
        "version": 3,
        "sources": [
          "/Users/afeng/Desktop/work/gdpayh5-web/src/pages/Auth/Country.vue?vue&type=script&setup=true&lang.ts"
        ],
        "sourcesContent": [
          "\"use strict\";\nimport { defineComponent as _defineComponent } from \"vue\";\nimport { createCommentVNode as _createCommentVNode, createElementVNode as _createElementVNode, resolveComponent as _resolveComponent, withCtx as _withCtx, createVNode as _createVNode, renderList as _renderList, Fragment as _Fragment, openBlock as _openBlock, createElementBlock as _createElementBlock, unref as _unref, toDisplayString as _toDisplayString, pushScopeId as _pushScopeId, popScopeId as _popScopeId } from \"vue\";\nconst _withScopeId = (n) => (_pushScopeId(\"data-v-d3f1b2ba\"), n = n(), _popScopeId(), n);\nconst _hoisted_1 = { class: \"country bg-[#fff] h-[100vh] z-[20000]\" };\nconst _hoisted_2 = /* @__PURE__ */ _withScopeId(() => /* @__PURE__ */ _createElementVNode(\n  \"div\",\n  { class: \"px-[20px]\" },\n  [\n    /* @__PURE__ */ _createElementVNode(\"p\", { class: \"h-[70px] text-[29px] mb-[10px] flex_s text-[#666666] border_p\" }, \"\\u56FD\\u5BB6/\\u5730\\u533A\")\n  ],\n  -1\n  /* HOISTED */\n));\nconst _hoisted_3 = [\"onClick\"];\nconst _hoisted_4 = [\"src\"];\nconst _hoisted_5 = { class: \"absolute right-[20px]\" };\nimport { requireImg } from \"@/utils/tools\";\nimport { showToast } from \"vant\";\nimport { ref } from \"vue\";\nimport { useRouter } from \"vue-router\";\nimport { wallet_type } from \"@/apis/auth\";\nimport { defineComponent } from \"vue\";\nconst fromPath = ref(\"/auth/login\");\nconst __default__ = defineComponent({\n  beforeRouteEnter(to, from, next) {\n    fromPath.value = from.path;\n    next((e) => {\n    });\n  }\n});\nexport default /* @__PURE__ */ _defineComponent({\n  ...__default__,\n  __name: \"Country\",\n  setup(__props) {\n    const router = useRouter();\n    const route = useRouter();\n    const value = ref(\"\");\n    const list = ref([]);\n    const list2 = ref([]);\n    let t = null;\n    const onSearch = (val) => {\n      clearTimeout(t);\n      t = setTimeout(() => {\n        if (!!!val) {\n          list.value = list2.value;\n        } else {\n          list.value = list2.value.filter((e) => {\n            return e.country_name.includes(val.toUpperCase()) || e.country_name.includes(val.toLowerCase()) || e.country_name.toLowerCase().includes(val.toLowerCase()) || e.country_name.toUpperCase().includes(val.toUpperCase()) || e.country_name.includes(val) || e.phone_code.includes(val.toLowerCase());\n          });\n        }\n      }, 500);\n    };\n    const oncancel = () => {\n      router.replace(fromPath.value);\n    };\n    const gopath = (item) => {\n      let path = fromPath.value + \"?country_code=\" + item.country_code + \"&phone_code=\" + +item.phone_code;\n      router.replace(path);\n    };\n    wallet_type({}).then((data) => {\n      if (!!!data.country_coin.length)\n        return showToast(\"\\u6570\\u636E\\u5F02\\u5E38\");\n      list.value = data.country_coin;\n      list2.value = data.country_coin;\n    });\n    return (_ctx, _cache) => {\n      const _component_van_search = _resolveComponent(\"van-search\");\n      return _openBlock(), _createElementBlock(\"div\", _hoisted_1, [\n        _createCommentVNode(' <form action=\"/\"> '),\n        _createVNode(_component_van_search, {\n          modelValue: value.value,\n          \"onUpdate:modelValue\": [\n            _cache[0] || (_cache[0] = ($event) => value.value = $event),\n            onSearch\n          ],\n          \"show-action\": \"\",\n          placeholder: \"\\u8BF7\\u8F93\\u5165\\u641C\\u7D22\\u5173\\u952E\\u8BCD\",\n          onSearch\n        }, {\n          action: _withCtx(() => [\n            _createElementVNode(\"div\", { onClick: oncancel }, \"\\u53D6\\u6D88\")\n          ]),\n          _: 1\n          /* STABLE */\n        }, 8, [\"modelValue\"]),\n        _createCommentVNode(\" </form> \"),\n        _hoisted_2,\n        _createElementVNode(\"ul\", null, [\n          (_openBlock(true), _createElementBlock(\n            _Fragment,\n            null,\n            _renderList(list.value, (item) => {\n              return _openBlock(), _createElementBlock(\"li\", {\n                class: \"flex_s w-[100%] h-[80px] text-[29px] px-[20px]\",\n                key: item.id,\n                onClick: ($event) => gopath(item)\n              }, [\n                _createElementVNode(\"img\", {\n                  class: \"h-[65%] mr-[13px]\",\n                  src: _unref(requireImg)(\"common/\" + item.country_code + \".png\"),\n                  alt: \"\"\n                }, null, 8, _hoisted_4),\n                _createElementVNode(\n                  \"span\",\n                  null,\n                  _toDisplayString(item.country_name),\n                  1\n                  /* TEXT */\n                ),\n                _createElementVNode(\n                  \"span\",\n                  _hoisted_5,\n                  _toDisplayString(item.phone_code),\n                  1\n                  /* TEXT */\n                )\n              ], 8, _hoisted_3);\n            }),\n            128\n            /* KEYED_FRAGMENT */\n          ))\n        ])\n      ]);\n    };\n  }\n});\n"
        ],
        "names": [],
        "mappings": ";AAAA;AACA;AACA;AACA;AACA;AACA;AACA;AACA;AACA;AACA;AACA;AACA;AACA;AACA;AACA;AACA;AACA;AACA;AACA;AACA;AACA;AACA;AACA;AACA;AACA;AACA;AACA;AACA;AACA;AACA;AACA;AACA;AACA;AACA;AACA;AACA;AACA;AACA;AACA;AACA;AACA;AACA;AACA;AACA;AACA;AACA;AACA;AACA;AACA;AACA;AACA;AACA;AACA;AACA;AACA;AACA;AACA;AACA;AACA;AACA;AACA;AACA;AACA;AACA;AACA;AACA;AACA;AACA,oCAAoC,uBAA+B;AACnE;AACA;AACA;AACA;AACA;AACA;AACA;AACA;AACA;AACA;AACA;AACA;AACA;AACA;AACA;AACA;AACA;AACA;AACA;AACA;AACA;AACA;AACA;AACA;AACA;AACA;AACA;AACA;AACA;AACA;AACA;AACA;AACA;AACA;AACA;AACA;AACA;AACA;AACA;AACA;AACA;AACA;AACA;AACA;AACA;AACA;AACA;AACA;AACA;AACA;AACA;AACA;AACA;AACA;AACA;AACA;AACA;AACA;AACA;"
      }
    },
    {
      "name": "vite:style-import",
      "start": 1714699771649,
      "end": 1714699771649,
      "order": "post"
    },
    {
      "name": "vite:build-import-analysis",
      "start": 1714699771649,
      "end": 1714699771649,
      "order": "normal"
    },
    {
      "name": "vite:reporter",
      "start": 1714699771649,
      "end": 1714699771649,
      "order": "normal"
    }
  ]
}
