{
  "resolvedId": "/Users/afeng/Desktop/work/gdpayh5-web/node_modules/.pnpm/xe-utils@3.5.24/node_modules/xe-utils/isFinite.js",
  "transforms": [
    {
      "name": "vite:load-fallback",
      "result": "var isNumber = require('./isNumber')\r\n\r\nfunction isNumberFinite (obj) {\r\n  return isNumber(obj) && isFinite(obj)\r\n}\r\n\r\nmodule.exports = isNumberFinite\r\n",
      "start": 1714699767612,
      "end": 1714699767643,
      "sourcemaps": null
    },
    {
      "name": "vite:css",
      "start": 1714699767643,
      "end": 1714699767643,
      "order": "normal"
    },
    {
      "name": "vite:esbuild",
      "start": 1714699767643,
      "end": 1714699767643,
      "order": "normal"
    },
    {
      "name": "vite:json",
      "start": 1714699767643,
      "end": 1714699767643,
      "order": "normal"
    },
    {
      "name": "vite:worker",
      "start": 1714699767643,
      "end": 1714699767643,
      "order": "normal"
    },
    {
      "name": "vite:vue",
      "start": 1714699767643,
      "end": 1714699767643,
      "order": "normal"
    },
    {
      "name": "vite:vue-jsx",
      "start": 1714699767643,
      "end": 1714699767643,
      "order": "normal"
    },
    {
      "name": "vite-plugin-vconsole",
      "result": "var isNumber = require('./isNumber')\r\n\r\nfunction isNumberFinite (obj) {\r\n  return isNumber(obj) && isFinite(obj)\r\n}\r\n\r\nmodule.exports = isNumberFinite\r\n",
      "start": 1714699767643,
      "end": 1714699767643,
      "order": "normal",
      "sourcemaps": null
    },
    {
      "name": "esbuild",
      "start": 1714699767643,
      "end": 1714699767643,
      "order": "normal"
    },
    {
      "name": "vite:define",
      "start": 1714699767643,
      "end": 1714699767643,
      "order": "normal"
    },
    {
      "name": "vite:css-post",
      "start": 1714699767643,
      "end": 1714699767643,
      "order": "normal"
    },
    {
      "name": "vite:build-html",
      "start": 1714699767643,
      "end": 1714699767643,
      "order": "normal"
    },
    {
      "name": "vite:worker-import-meta-url",
      "start": 1714699767643,
      "end": 1714699767643,
      "order": "normal"
    },
    {
      "name": "vite:asset-import-meta-url",
      "start": 1714699767643,
      "end": 1714699767643,
      "order": "normal"
    },
    {
      "name": "commonjs",
      "result": "import * as commonjsHelpers from \"\u0000commonjsHelpers.js\";\nimport require$$0 from \"\\u0000/Users/afeng/Desktop/work/gdpayh5-web/node_modules/.pnpm/xe-utils@3.5.24/node_modules/xe-utils/isNumber.js?commonjs-proxy\";\n\nvar isNumber = require$$0\r\n\r\nfunction isNumberFinite (obj) {\r\n  return isNumber(obj) && isFinite(obj)\r\n}\r\n\r\nvar _isFinite = isNumberFinite\n\nexport default /*@__PURE__*/commonjsHelpers.getDefaultExportFromCjs(_isFinite);\nexport { _isFinite as __moduleExports };",
      "start": 1714699767643,
      "end": 1714699768089,
      "order": "normal",
      "sourcemaps": {
        "version": 3,
        "sources": [
          ""
        ],
        "names": [],
        "mappings": ";;;AAAA,IAAI,QAAQ,GAAG,UAAqB;AACpC;AACA,SAAS,cAAc,EAAE,GAAG,EAAE;AAC9B,EAAE,OAAO,QAAQ,CAAC,GAAG,CAAC,IAAI,QAAQ,CAAC,GAAG,CAAC;AACvC,CAAC;AACD;IACA,SAAc,GAAG"
      }
    },
    {
      "name": "vite:dynamic-import-vars",
      "start": 1714699768089,
      "end": 1714699768089,
      "order": "normal"
    },
    {
      "name": "vite:import-glob",
      "start": 1714699768089,
      "end": 1714699768089,
      "order": "normal"
    },
    {
      "name": "unplugin-auto-import",
      "start": 1714699768089,
      "end": 1714699768089,
      "order": "post"
    },
    {
      "name": "unplugin-vue-components",
      "start": 1714699768089,
      "end": 1714699768089,
      "order": "post"
    },
    {
      "name": "vite:style-import",
      "start": 1714699768089,
      "end": 1714699768089,
      "order": "post"
    },
    {
      "name": "vite:build-import-analysis",
      "start": 1714699768089,
      "end": 1714699768089,
      "order": "normal"
    },
    {
      "name": "vite:reporter",
      "start": 1714699768089,
      "end": 1714699768089,
      "order": "normal"
    }
  ]
}
